sqlview/__init__.py
sqlview/command.py
sqlview/reader.py
sqlview/utils.py
sqlview-0.23.9.0.dist-info/LICENSE
sqlview-0.23.9.0.dist-info/METADATA
sqlview-0.23.9.0.dist-info/WHEEL
sqlview-0.23.9.0.dist-info/entry_points.txt
sqlview-0.23.9.0.dist-info/top_level.txt
sqlview-0.23.9.0.dist-info/RECORD
